ali_sms_api/__init__.py
ali_sms_api/base.py
ali_sms_api/gen.py
ali_sms_api/py_test_sms.py
ali_sms_api-0.3.1.dist-info/WHEEL
ali_sms_api-0.3.1.dist-info/METADATA
ali_sms_api-0.3.1.dist-info/RECORD
