Metadata-Version: 2.1
Name: ali-sms-api
Version: 0.3.1
Summary: 阿里云 短信 SDK
Author: dev
Author-email: dev@qiyutech.tech
Requires-Python: >=3.8,<4.0
Classifier: Programming Language :: Python :: 3
Classifier: Programming Language :: Python :: 3.8
Classifier: Programming Language :: Python :: 3.9
Requires-Dist: aiohttp (>=3.7,<4)
Requires-Dist: pydantic (>=1.6,<2)
Requires-Dist: requests (>=2.24,<3)
